PyMPDATA/__init__.py
PyMPDATA/options.py
PyMPDATA/scalar_field.py
PyMPDATA/solver.py
PyMPDATA/stepper.py
PyMPDATA/vector_field.py
PyMPDATA/boundary_conditions/__init__.py
PyMPDATA/boundary_conditions/constant.py
PyMPDATA/boundary_conditions/extrapolated.py
PyMPDATA/boundary_conditions/periodic.py
PyMPDATA/boundary_conditions/polar.py
PyMPDATA/impl/__init__.py
PyMPDATA/impl/clock.py
PyMPDATA/impl/domain_decomposition.py
PyMPDATA/impl/enumerations.py
PyMPDATA/impl/field.py
PyMPDATA/impl/formulae_antidiff.py
PyMPDATA/impl/formulae_axpy.py
PyMPDATA/impl/formulae_flux.py
PyMPDATA/impl/formulae_laplacian.py
PyMPDATA/impl/formulae_nonoscillatory.py
PyMPDATA/impl/formulae_upwind.py
PyMPDATA/impl/grid.py
PyMPDATA/impl/indexers.py
PyMPDATA/impl/meta.py
PyMPDATA/impl/traversals.py
PyMPDATA/impl/traversals_common.py
PyMPDATA/impl/traversals_halos_scalar.py
PyMPDATA/impl/traversals_halos_vector.py
PyMPDATA/impl/traversals_scalar.py
PyMPDATA/impl/traversals_vector.py
pympdata-1.6.3.dist-info/licenses/LICENSE
pympdata-1.6.3.dist-info/METADATA
pympdata-1.6.3.dist-info/WHEEL
pympdata-1.6.3.dist-info/top_level.txt
pympdata-1.6.3.dist-info/RECORD
