Metadata-Version: 2.4
Name: pympdata
Version: 1.6.3
Summary: Numba-accelerated Pythonic implementation of MPDATA with examples in Python, Julia, Rust and Matlab
Author: https://github.com/open-atmos/PyMPDATA/graphs/contributors
Author-email: sylwester.arabas@agh.edu.pl
License: GPL-3.0
Project-URL: Tracker, https://github.com/open-atmos/PyMPDATA/issues
Project-URL: Documentation, https://open-atmos.github.io/PyMPDATA
Project-URL: Source, https://github.com/open-atmos/PyMPDATA
Keywords: atmospheric-modelling,numba,numerical-integration,advection,pde-solver,advection-diffusion
Classifier: Development Status :: 4 - Beta
Classifier: Intended Audience :: Science/Research
Classifier: License :: OSI Approved :: GNU General Public License v3 (GPLv3)
Classifier: Operating System :: OS Independent
Classifier: Programming Language :: Python :: 3
Classifier: Topic :: Scientific/Engineering
Classifier: Topic :: Scientific/Engineering :: Atmospheric Science
Classifier: Topic :: Scientific/Engineering :: Mathematics
Classifier: Topic :: Scientific/Engineering :: Physics
Classifier: Topic :: Software Development :: Libraries
License-File: LICENSE
Requires-Dist: numba
Requires-Dist: numpy
Requires-Dist: pystrict
Provides-Extra: tests
Requires-Dist: PyMPDATA-examples; extra == "tests"
Requires-Dist: pillow; extra == "tests"
Requires-Dist: matplotlib; extra == "tests"
Requires-Dist: scipy; extra == "tests"
Requires-Dist: jupyter-core; extra == "tests"
Requires-Dist: jupyter_client; extra == "tests"
Requires-Dist: ipywidgets; extra == "tests"
Requires-Dist: ipykernel; extra == "tests"
Requires-Dist: ghapi; extra == "tests"
Requires-Dist: pytest; extra == "tests"
Requires-Dist: pytest-benchmark; extra == "tests"
Requires-Dist: joblib; extra == "tests"
Requires-Dist: imageio; extra == "tests"
Requires-Dist: nbformat; extra == "tests"
Requires-Dist: pyparsing; extra == "tests"
Dynamic: author
Dynamic: author-email
Dynamic: classifier
Dynamic: description
Dynamic: description-content-type
Dynamic: keywords
Dynamic: license
Dynamic: license-file
Dynamic: project-url
Dynamic: provides-extra
Dynamic: requires-dist
Dynamic: summary
